pandoc_flow/__init__.py
pandoc_flow/__main__.py
pandoc_flow/__version__.py
pandoc_flow/cli.py
pandoc_flow/const.py
pandoc_flow/core.py
pandoc_flow/pipeline.py
pandoc_flow/processors/__init__.py
pandoc_flow/processors/jinja2.py
pandoc_flow/processors/pandoc.py
pandoc_flow-1.1.1.dist-info/METADATA
pandoc_flow-1.1.1.dist-info/WHEEL
pandoc_flow-1.1.1.dist-info/top_level.txt
pandoc_flow-1.1.1.dist-info/RECORD
