Metadata-Version: 2.1
Name: pandoc-flow
Version: 1.1.1
Summary: Pandoc Flow - Augments Pandoc with advanced pre-processing, automates routine
Home-page: https://github.com/corvis/pandoc-flow
Author: Dmitry Berezovsky
License: MIT
Keywords: pandoc pre-process processing pipiline document generator
Platform: UNKNOWN
Classifier: Development Status :: 3 - Alpha
Classifier: Intended Audience :: Developers
Classifier: Topic :: Software Development :: Libraries :: Python Modules
Classifier: Topic :: Home Automation
Classifier: License :: OSI Approved :: MIT License
Classifier: Programming Language :: Python :: 3
Classifier: Programming Language :: Python :: 3.6
Classifier: Programming Language :: Python :: 3.7
Classifier: Programming Language :: Python :: 3.8
Classifier: Programming Language :: Python :: 3.9
Requires-Python: >3.6
Requires-Dist: strome (~=1.0.0)
